MANIFEST.in
README.md
pyproject.toml
setup.py
cyquant/__init__.py
cyquant/ctypes.pxd
cyquant/dimensions.cpp
cyquant/dimensions.pxd
cyquant/dimensions.pyx
cyquant/format_quantity.py
cyquant/qmath.cpp
cyquant/qmath.pyx
cyquant/quantities.cpp
cyquant/quantities.pxd
cyquant/quantities.pyx
cyquant/si.py
cyquant/util.cpp
cyquant/util.pyx
cyquantx.egg-info/PKG-INFO
cyquantx.egg-info/SOURCES.txt
cyquantx.egg-info/dependency_links.txt
cyquantx.egg-info/not-zip-safe
cyquantx.egg-info/requires.txt
cyquantx.egg-info/top_level.txt