Metadata-Version: 2.1
Name: cyquantx
Version: 1.1.0
Summary: cython dimensional analysis and unit tracking utility
Author-email: Greg Echelberger <gechelberger@gmail.com>
Keywords: c-extension,SI,units,quantities,dimensional analysis
Classifier: Programming Language :: Python
Classifier: Programming Language :: Python :: 3
Classifier: Programming Language :: Cython
Classifier: Topic :: Scientific/Engineering
Classifier: Intended Audience :: Developers
Classifier: Intended Audience :: Science/Research
Requires-Python: >=3.9
Provides-Extra: tests
Provides-Extra: dev
